Metadata-Version: 2.4
Name: mcp-server-weather-luht
Version: 0.1.0
Summary: 实现类weather功能的MCP工具
Requires-Python: >=3.12
Requires-Dist: dotenv>=0.9.9
Requires-Dist: mcp>=1.10.1
Requires-Dist: openai>=1.93.0
Requires-Dist: asyncio>=3.4.3
Requires-Dist: openai-agents>=0.0.12
Requires-Dist: pydantic>=2.11.3
Requires-Dist: typing>=3.10.0.0
